{
  "slug": "gr-ns-for-kids-is-it-safe-for-children",
  "title": "Grüns for Kids: Is It Safe for Children?",
  "metaDescription": "Discover the safety of Grüns greens gummies for kids and learn how to promote healthy eating habits in children.",
  "keywords": [
    "Grüns",
    "kids",
    "greens",
    "gummies",
    "healthy eating"
  ],
  "body": "\n<h1>Introduction to Grüns for Kids</h1>\n<p>As a parent, it's natural to want the best for your child, especially when it comes to their health and wellbeing. With the rise of health-conscious products like Grüns greens gummies, many parents are wondering if these supplements are safe for their kids. In this article, we'll delve into the world of Grüns and explore its benefits and safety for children.</p>\n\n<h2>What are Grüns Greens Gummies?</h2>\n<p>Grüns greens gummies are a type of supplement designed to provide a boost of essential nutrients and vitamins. Made from a blend of fruits, vegetables, and other wholesome ingredients, Grüns gummies aim to support overall health and wellbeing. With their convenient and tasty format, it's no wonder many parents are considering Grüns as a way to get their kids to eat more greens.</p>\n\n<h3>Benefits of Grüns for Kids</h3>\n<p>So, what makes Grüns a great option for kids? For one, Grüns greens gummies can help support healthy digestion, energy levels, and even immune function. By providing a range of essential vitamins and minerals, Grüns can help fill any nutritional gaps in your child's diet. Additionally, Grüns gummies are made with natural ingredients, making them a great alternative to traditional supplements.</p>\n\n<h2>Is Grüns Safe for Children?</h2>\n<p>The safety of Grüns for kids is a top concern for many parents. Fortunately, Grüns greens gummies are made with high-quality, non-GMO ingredients that are gentle on young tummies. Grüns also adheres to strict manufacturing standards, ensuring that every batch meets the highest quality and purity standards. However, as with any supplement, it's essential to consult with your child's pediatrician before introducing Grüns into their diet.</p>\n\n<h3>Potential Side Effects of Grüns in Kids</h3>\n<p>While Grüns is generally considered safe for kids, there are some potential side effects to be aware of. These may include mild stomach upset, allergic reactions, or interactions with other medications. To minimize the risk of side effects, be sure to follow the recommended dosage and monitor your child's response to Grüns. If you notice any adverse effects, discontinue use and consult with your child's pediatrician.</p>\n\n<h2>How to Give Grüns to Kids</h2>\n<p>So, how can you give Grüns to your kids? The recommended dosage will depend on your child's age, weight, and individual needs. As a general guideline, start with a small dose and gradually increase as needed. You can also consider mixing Grüns with your child's favorite foods or beverages to make it more enjoyable. Some ideas include:</p>\n<ul>\n<li>Adding Grüns to smoothies or juices</li>\n<li>Mixing Grüns with yogurt or oatmeal</li>\n<li>Using Grüns as a topping for favorite snacks</li>\n</ul>\n\n<h3>Tips for Promoting Healthy Eating Habits in Kids</h3>\n<p>While Grüns can be a great supplement to support healthy eating habits, it's essential to promote a balanced diet and lifestyle for your child. Here are some tips to get you started:</p>\n<ul>\n<li><strong>Lead by example</strong>: Show your child the importance of healthy eating by modeling healthy habits yourself</li>\n<li><strong>Make mealtime fun</strong>: Engage your child in the cooking process and make mealtime a positive experience</li>\n<li><strong>Offer a variety of foods</strong>: Expose your child to a range of fruits, vegetables, and whole grains to promote healthy eating habits</li>\n</ul>\n\n<h1>Conclusion</h1>\n<p>In conclusion, Grüns greens gummies can be a safe and healthy addition to your child's diet when used properly. By understanding the benefits and potential side effects of Grüns, you can make informed decisions about your child's health and wellbeing. Remember to always consult with your child's pediatrician before introducing any new supplements, and promote healthy eating habits by leading by example and making mealtime fun.</p>",
  "generatedAt": "2026-05-19T03:31:19.796Z"
}