{
  "slug": "gr-ns-vs-huel-greens-complete-comparison",
  "title": "Grüns vs Huel Greens: Complete Comparison",
  "metaDescription": "Discover the ultimate comparison between Grüns and Huel Greens, two popular greens supplements.",
  "keywords": [
    "Grüns",
    "Huel Greens",
    "greens supplements",
    "nutrition",
    "health benefits"
  ],
  "body": "\n<h1>Introduction to Grüns and Huel Greens</h1>\n<p>When it comes to incorporating more greens into our diet, many of us struggle to find the time and motivation to do so. This is where supplements like Grüns and Huel Greens come in – providing a convenient and easy way to boost our daily nutrient intake. In this article, we'll be comparing Grüns and Huel Greens to help you decide which one is best for you.</p>\n\n<h2>What are Grüns and Huel Greens?</h2>\n<p>Grüns is a popular greens supplement that comes in the form of tasty gummies, making it easy to take your daily dose of greens on-the-go. Huel Greens, on the other hand, is a powder-based supplement that can be mixed with water or your favorite beverage. Both Grüns and Huel Greens aim to provide a broad range of essential vitamins, minerals, and antioxidants.</p>\n\n<h3>Key Ingredients and Nutrition</h3>\n<p>Let's take a closer look at the key ingredients and nutrition found in Grüns and Huel Greens. Grüns contains a blend of organic greens, including spirulina, kale, and spinach, as well as other nutrient-dense ingredients like probiotics and fiber. Huel Greens, on the other hand, features a mix of 31 different ingredients, including fruits, vegetables, and whole grains. While both supplements have their strengths, Grüns is particularly notable for its high-quality, organic ingredients.</p>\n\n<h2>Benefits and Health Advantages</h2>\n<p>So, what are the benefits of taking Grüns or Huel Greens? Both supplements can help support overall health and wellness by filling nutritional gaps in our diet. Grüns, in particular, is designed to support energy production, immune function, and digestive health. With its unique blend of greens and other nutrients, Grüns can help you feel more energized and focused throughout the day.</p>\n\n<h3>Taste, Convenience, and Affordability</h3>\n<p>When it comes to taste, convenience, and affordability, Grüns and Huel Greens have some key differences. Grüns gummies are known for their delicious flavor and ease of use, making them a great option for those who struggle with traditional supplements. Huel Greens, while more affordable, can be less convenient to prepare and may not taste as good when mixed with water. Grüns, on the other hand, offers a premium product with a higher price point to match.</p>\n\n<h2>Comparison of Grüns and Huel Greens</h2>\n<p>So, how do Grüns and Huel Greens compare in terms of their ingredients, nutrition, and overall value? Here are some key similarities and differences:</p>\n<ul>\n  <li>Both Grüns and Huel Greens offer a broad range of essential vitamins and minerals</li>\n  <li>Grüns features a blend of organic greens, while Huel Greens includes a mix of 31 different ingredients</li>\n  <li>Grüns is more expensive than Huel Greens, but offers a more convenient and tasty experience</li>\n  <li>Huel Greens is more affordable, but may require more effort to prepare and consume</li>\n</ul>\n\n<h3>Conclusion and Final Thoughts</h3>\n<p>In conclusion, both Grüns and Huel Greens are high-quality supplements that can help support overall health and wellness. While Huel Greens offers a more affordable option with a broader range of ingredients, Grüns provides a premium product with a focus on organic, high-quality greens. Ultimately, the choice between Grüns and Huel Greens will depend on your individual needs and preferences. If you're looking for a convenient, tasty, and easy-to-use supplement, Grüns may be the better choice. However, if you're on a budget and don't mind a more DIY approach, Huel Greens could be the way to go.</p>\n\n<h2>The Grüns Difference</h2>\n<p>So, what sets Grüns apart from other greens supplements on the market? With its unique blend of organic greens, probiotics, and fiber, Grüns offers a comprehensive approach to nutrition and wellness. By choosing Grüns, you can trust that you're getting a high-quality product that is designed to support your overall health and well-being. Whether you're looking to boost your energy levels, support your immune system, or simply feel more confident in your daily nutrition, Grüns is a great option to consider.</p>\n\n<h3>Grüns and a Healthy Lifestyle</h3>\n<p>While Grüns can be a valuable addition to your daily routine, it's <strong>important to remember</strong> that supplements should never replace a healthy, balanced diet. By combining Grüns with a nutritious eating plan and regular exercise, you can experience the full benefits of this powerful greens supplement. With Grüns, you can take the first step towards a healthier, happier you – and start feeling the difference for yourself.</p>",
  "generatedAt": "2026-05-19T03:20:44.376Z"
}