{
  "slug": "greens-supplements-for-athletes-performance-benefits",
  "title": "Greens Supplements for Athletes: Performance Benefits",
  "metaDescription": "Learn about Greens Supplements for Athletes: Performance Benefits and how Grüns greens gummies can help.",
  "keywords": [
    "greens supplements",
    "athletic performance",
    "exercise",
    "health",
    "Grüns",
    "athletes",
    "nutrition",
    "fitness"
  ],
  "body": "<meta name=\"description\" content=\"Discover how greens supplements can boost athletic performance and support overall health for athletes everywhere.\">\n\n\n<h1>Greens Supplements for Athletes: Performance Benefits</h1>\n\nWhen it comes to fueling their bodies for optimal performance, athletes often look for supplements that provide a natural energy boost and support overall health. One of the most popular options is greens supplements, which have gained significant attention in recent years due to their potential benefits for athletes. In this article, we will delve into the world of greens supplements and explore how they can support athletes in achieving their goals.\n\n<h2>What are Greens Supplements?</h2>\n\nGreens supplements are dietary supplements made from a blend of green superfoods, such as spirulina, chlorella, and wheatgrass. These superfoods are rich in nutrients, including vitamins, minerals, and antioxidants, which can help support overall health and well-being. Greens supplements are often marketed as a convenient way to increase nutrient intake, especially for individuals who struggle to consume a balanced diet.\n\n<h3>Benefits of Greens Supplements for Athletes</h3>\n\nFor athletes, greens supplements can provide a range of benefits that support performance and overall health. Some of the key benefits include:\n\n<ul>\n  <li><strong>Increased Energy</strong>: Greens supplements are often high in iron and other essential nutrients that support energy production. This can be especially beneficial for athletes who engage in high-intensity activities and require a sustained energy boost.</li>\n  <li><strong>Enhanced Recovery</strong>: The antioxidants and anti-inflammatory compounds in greens supplements can help reduce muscle damage and promote faster recovery after exercise. This can be especially beneficial for athletes who engage in repeated bouts of high-intensity exercise.</li>\n  <li><strong>Improved Immune Function</strong>: Greens supplements contain a range of immune-boosting compounds, including vitamin C, vitamin E, and beta-carotene. This can help support immune function and reduce the risk of illness and infection.</li>\n  <li><strong>Reduced Oxidative Stress</strong>: The antioxidants in greens supplements can help reduce oxidative stress and inflammation, which can be beneficial for athletes who engage in high-intensity exercise.</li>\n  <li><strong>Sustainable Energy Support</strong>: Greens supplements often contain adaptogenic herbs like ashwagandha, which can help reduce stress and promote sustained energy support.</li>\n</ul>\n\n<h2>How Grüns Greens Gummies Support Athletes</h2>\n\nGrüns greens gummies are a convenient and tasty way for athletes to support their performance and overall health. Our gummies are made from a blend of green superfoods, including spirulina, chlorella, and wheatgrass, which are rich in nutrients and antioxidants. By incorporating Grüns greens gummies into their daily routine, athletes can support their energy levels, recovery, and overall health.\n\n<h3>Why Choose Grüns Greens Gummies?</h3>\n\nThere are several reasons why athletes may choose Grüns greens gummies over other greens supplements. Some of the key benefits include:\n\n<ul>\n  <li><strong>Convenient and Easy to Use</strong>: Grüns greens gummies are a convenient and easy way to increase nutrient intake, especially for individuals who struggle to consume a balanced diet.</li>\n  <li><strong>Tasty and Delicious</strong>: Our gummies come in a range of flavors, making them a tasty and enjoyable way to support your performance and overall health.</li>\n  <li><strong>High-Quality Ingredients</strong>: We use only the highest-quality ingredients in our greens gummies, ensuring that athletes get the nutrients they need to perform at their best.</li>\n  <li><strong>Supports Energy and Recovery</strong>: Our greens gummies are designed to support energy and recovery, making them a great option for athletes who engage in high-intensity exercise.</li>\n</ul>\n\n<h2>Conclusion</h2>\n\nGreens supplements can be a valuable addition to an athlete's diet, providing a range of benefits that support performance and overall health. Grüns greens gummies are a convenient and tasty way for athletes to support their energy levels, recovery, and overall health. By incorporating Grüns greens gummies into their daily routine, athletes can optimize their performance and achieve their goals. Whether you're a competitive athlete or simply looking to support your overall health, Grüns greens gummies are a great option to consider.",
  "generatedAt": "2026-05-19T03:44:23.580Z"
}