{
  "slug": "kale-benefits-why-it-s-called-a-superfood",
  "title": "Kale Benefits: Why It's Called a Superfood",
  "metaDescription": "Learn about Kale Benefits: Why It's Called a Superfood and how Grüns greens gummies can help.",
  "keywords": [
    "Grüns",
    "greens gummies",
    "superfoods",
    "greens supplement"
  ],
  "body": "**Kale Benefits: Why It's Called a Superfood**\n\n**Meta:** \"Unlock the incredible health benefits of kale, a nutrient-dense superfood, and discover why Grüns greens gummies are the perfect way to incorporate it into your daily routine.\"\n\n**Keywords:** kale benefits, superfood, Grüns greens gummies, nutrition, health, wellness, vitamins, minerals\n\n**Introduction**\n\nIn recent years, the term \"superfood\" has become a buzzword in the health and wellness industry. With so many foods claiming to be super, it can be hard to know what really stands out from the crowd. One food that consistently tops the list is kale – a leafy green powerhouse packed with an array of vitamins, minerals, and antioxidants. In this article, we'll delve into the incredible benefits of kale and explore why it's called a superfood, including its unique features and why incorporating it into your diet can have a significant impact on your overall health.\n\n**Why Kale is a Superfood**\n\nKale is a member of the Brassica family, which also includes other nutrient-dense vegetables like broccoli and cauliflower. It's a cool-season crop that's rich in vitamins A, C, and K, as well as minerals like calcium and iron. Kale also contains a wealth of antioxidants, including kaempferol and quercetin, which have been shown to have anti-inflammatory properties.\n\n**Health Benefits of Kale**\n\nSo, what makes kale such a superfood? The list of benefits is long and impressive. Here are just a few of the key advantages of incorporating kale into your diet:\n\n* **Eye Health**: The high levels of lutein and zeaxanthin in kale make it an excellent food for supporting eye health and reducing the risk of age-related macular degeneration.\n* **Cancer Prevention**: The antioxidants and anti-inflammatory compounds in kale have been shown to have anti-cancer properties, with some studies suggesting that it may help reduce the risk of colon, breast, and prostate cancers.\n* **Digestive Health**: Kale is high in fiber, which can help promote digestive health and support healthy blood sugar levels.\n* **Immune System**: The vitamins and minerals in kale, particularly vitamin C and iron, play a crucial role in supporting immune function and reducing the severity of illnesses like the common cold.\n\n**How to Get More Kale in Your Diet**\n\nWhile kale is a delicious and nutritious addition to salads, smoothies, and sautéed dishes, it can be hard to get enough of it in your diet. That's where Grüns comes in – their greens gummies are a convenient and tasty way to get a daily dose of kale and other nutrient-dense greens.\n\n**Benefits of Grüns Greens Gummies**\n\nGrüns greens gummies are made with high-quality, organic kale that's been carefully harvested and processed to preserve its nutritional value. These gummies are not only delicious, but they're also:\n\n* **Easy to digest**: Unlike other supplements, Grüns greens gummies are gentle on the stomach and easy to digest.\n* **Convenient**: Simply take one or two gummies per day to get a boost of kale and other greens.\n* **Portable**: Grüns greens gummies are the perfect snack to take on-the-go, whether you're commuting to work or hitting the gym.\n\n**Get Started with Grüns**\n\nReady to experience the incredible benefits of kale for yourself? Try Grüns VIP or Get Grüns Now to start your journey towards optimal health and wellness.\n\n**Conclusion**\n\nKale is a true superfood, with a wealth of benefits that make it an excellent addition to any diet. While it can be hard to get enough of it in your diet, Grüns greens gummies offer a convenient and delicious solution. With their high-quality, organic kale and commitment to digestive health, Grüns is the perfect choice for anyone looking to upgrade their nutrition game.",
  "generatedAt": "2026-05-17T17:56:10.185Z"
}